multigrate/__init__.py
multigrate/data/__init__.py
multigrate/data/_preprocessing.py
multigrate/dataloaders/__init__.py
multigrate/dataloaders/_ann_dataloader.py
multigrate/dataloaders/_data_splitting.py
multigrate/distributions/__init__.py
multigrate/distributions/_mmd.py
multigrate/model/__init__.py
multigrate/model/_multivae.py
multigrate/module/__init__.py
multigrate/module/_multivae_torch.py
multigrate/nn/__init__.py
multigrate/nn/_base_components.py
multigrate-0.0.2.dist-info/METADATA
multigrate-0.0.2.dist-info/WHEEL
multigrate-0.0.2.dist-info/licenses/LICENSE
multigrate-0.0.2.dist-info/RECORD
