Metadata-Version: 2.1
Name: multigrate
Version: 0.0.2
Summary: Multigrate: multimodal data integration for single-cell genomics.
Project-URL: Documentation, https://multigrate.readthedocs.io/
Project-URL: Source, https://github.com/theislab/multigrate
Project-URL: Home-page, https://github.com/theislab/multigrate
Author: Anastasia Litinetskaya
Maintainer-email: Anastasia Litinetskaya <alitinet@gmail.com>
License: BSD 3-Clause License
License-File: LICENSE
Requires-Python: <3.11,>=3.9
Requires-Dist: matplotlib
Requires-Dist: scanpy
Requires-Dist: scvi-tools
Provides-Extra: dev
Requires-Dist: bump2version; extra == 'dev'
Requires-Dist: pre-commit; extra == 'dev'
Provides-Extra: doc
Requires-Dist: furo; extra == 'doc'
Requires-Dist: ipykernel; extra == 'doc'
Requires-Dist: leidenalg; extra == 'doc'
Requires-Dist: louvain; extra == 'doc'
Requires-Dist: muon; extra == 'doc'
Requires-Dist: myst-parser; extra == 'doc'
Requires-Dist: nbsphinx; extra == 'doc'
Requires-Dist: notebook; extra == 'doc'
Requires-Dist: python-igraph; extra == 'doc'
Requires-Dist: scanpy==1.9.0; extra == 'doc'
Requires-Dist: scanpydoc[typehints]>=0.7.4; extra == 'doc'
Requires-Dist: sphinx>=4; extra == 'doc'
Requires-Dist: sphinxcontrib-bibtex>=1.0.0; extra == 'doc'
Provides-Extra: test
Requires-Dist: pytest; extra == 'test'
Requires-Dist: pytest-cov; extra == 'test'
